{
    "code": 0,
    "subcode": 0,
    "message": "",
    "default": 0,
    "data": {
        "total": 3,
        "comments": [
            {
                "id": 1,
                "postTime": 1477374666,
                "effect": 1024,
                "replyNum": 0,
                "content": "厉害了我的哥 ",
                "capacity": 12157,
                "poster": {
                    "id": "785535171",
                    "platform": 1,
                    "name": "Jの星愿 ",
                    "emoji": []
                },
                "bmp": "18d095a40100a201",
                "ismyreply": 0,
                "replies": []
            },
            {
                "id": 2,
                "postTime": 1477386524,
                "effect": 1024,
                "replyNum": 0,
                "content": "难以置信 ",
                "capacity": 12162,
                "poster": {
                    "id": "978632333",
                    "platform": 1,
                    "name": "特种兵-何骐 ",
                    "emoji": []
                },
                "bmp": "98c09da00002e121",
                "ismyreply": 0,
                "replies": []
            },
            {
                "id": 3,
                "postTime": 1477407545,
                "effect": 1024,
                "replyNum": 0,
                "content": "先去techstop要一台手机用着 ",
                "capacity": 12142,
                "poster": {
                    "id": "122155302",
                    "platform": 1,
                    "name": "木子日匀 ",
                    "emoji": []
                },
                "bmp": "38d40da00102c209",
                "ismyreply": 0,
                "replies": []
            }
        ]
    }
}