{
    "code": 0,
    "subcode": 0,
    "message": "",
    "default": 0,
    "data": {
        "total": 2,
        "comments": [
            {
                "id": 1,
                "postTime": 1471928530,
                "effect": 1024,
                "replyNum": 0,
                "content": "那只小萝莉会不会是小音呢(。&#8226;﹃ &#8226;。) ",
                "capacity": 12109,
                "poster": {
                    "id": "464388324",
                    "platform": 1,
                    "name": "音 ",
                    "emoji": []
                },
                "bmp": "18d19d880102e021",
                "ismyreply": 0,
                "replies": []
            },
            {
                "id": 2,
                "postTime": 1471941029,
                "effect": 1056,
                "replyNum": 2,
                "content": "那只小萝莉会不会是小雪呢(。&#8226;﹃ &#8226;。) ",
                "capacity": 11867,
                "poster": {
                    "id": "1158739473",
                    "platform": 1,
                    "name": "小音的小雪姐姐 ",
                    "emoji": []
                },
                "bmp": "18849d88080cd201",
                "ismyreply": 0,
                "replies": [
                    {
                        "poster": {
                            "id": "464388324",
                            "name": "音 ",
                            "platform": 1
                        },
                        "content": "@{uin:1158739473,nick:小音的小雪姐姐,who:1,auto:1}你明明是那个“大”盒装的，我才是“小”萝莉(￣～￣) ",
                        "postTime": 1471943224,
                        "id": 1471943224,
                        "effect": 0
                    },
                    {
                        "poster": {
                            "id": "1158739473",
                            "name": "小音的小雪姐姐 ",
                            "platform": 1
                        },
                        "content": "@{uin:464388324,nick:音,who:1,auto:1}哼人家会变得越来越瘦（受）的！ ",
                        "postTime": 1471943505,
                        "id": 1471943505,
                        "effect": 0
                    }
                ]
            }
        ]
    }
}