{
    "code": 0,
    "subcode": 0,
    "message": "",
    "default": 0,
    "data": {
        "limit": 0,
        "photoList": [
            {
                "batchId": "0",
                "browser": 0,
                "cameratype": "",
                "cp_flag": false,
                "cp_x": 0,
                "cp_y": 0,
                "desc": "",
                "exif": {
                    "exposureCompensation": "",
                    "exposureMode": "",
                    "exposureProgram": "",
                    "exposureTime": "",
                    "flash": "",
                    "fnumber": "",
                    "focalLength": "",
                    "iso": "",
                    "lensModel": "",
                    "make": "",
                    "meteringMode": "",
                    "model": "",
                    "originalTime": ""
                },
                "forum": 0,
                "frameno": 0,
                "height": 450,
                "id": 0,
                "is_video": false,
                "is_weixin_mode": 0,
                "ismultiup": 0,
                "lloc": "M3d.zlfb00jTnDJ*DfT1I93UMwYf6wsAAA!!",
                "modifytime": 1280925178,
                "name": "p_large_rjCd_7b3b000021fb2d10",
                "origin": 0,
                "origin_upload": 0,
                "origin_url": "",
                "owner": "251815992",
                "ownername": "251815992",
                "photocubage": 137428,
                "phototype": 1,
                "picmark_flag": 0,
                "picrefer": 3,
                "platformId": 0,
                "platformSubId": 0,
                "poiName": "",
                "pre": "http://b52.photo.store.qq.com/psu?/cefafb6d-3040-48a7-8dfb-b5847497ea4a/8NZMpoktbQUr76yVg5JltJWTLbEqKHXhIXGcmJTRBJk!/m/Yd8DQR0KDgAAYtQzBh*rCwAA&a=49&b=52&bo=WALCAQAAAAABA70!",
                "raw": "",
                "raw_upload": 0,
                "rawshoottime": 0,
                "shoottime": 0,
                "shorturl": "",
                "sloc": "M0zv3ps3oE6UnsXt521AxfTfA0EdCg4AAA!!",
                "tag": "",
                "uploadtime": "2010-08-04 20:32:58",
                "url": "http://b52.photo.store.qq.com/psu?/cefafb6d-3040-48a7-8dfb-b5847497ea4a/8NZMpoktbQUr76yVg5JltJWTLbEqKHXhIXGcmJTRBJk!/b/Yd8DQR0KDgAAYtQzBh*rCwAA&a=49&b=52&bo=WALCAQAAAAABA70!",
                "width": 600,
                "yurl": 0
            },
            {
                "batchId": "0",
                "browser": 0,
                "cameratype": "",
                "cp_flag": false,
                "cp_x": 0,
                "cp_y": 0,
                "desc": "",
                "exif": {
                    "exposureCompensation": "",
                    "exposureMode": "",
                    "exposureProgram": "",
                    "exposureTime": "",
                    "flash": "",
                    "fnumber": "",
                    "focalLength": "",
                    "iso": "",
                    "lensModel": "",
                    "make": "",
                    "meteringMode": "",
                    "model": "",
                    "originalTime": ""
                },
                "forum": 0,
                "frameno": 0,
                "height": 800,
                "id": 0,
                "is_video": false,
                "is_weixin_mode": 0,
                "ismultiup": 0,
                "lloc": "MyRb8Ps2xkzNglImbnM0nbQQg9UaulsAAA!!",
                "modifytime": 1280730597,
                "name": "IMG_0033",
                "origin": 0,
                "origin_upload": 0,
                "origin_url": "",
                "owner": "251815992",
                "ownername": "251815992",
                "photocubage": 102377,
                "phototype": 1,
                "picmark_flag": 0,
                "picrefer": 1,
                "platformId": 0,
                "platformSubId": 0,
                "poiName": "",
                "pre": "http://b45.photo.store.qq.com/psu?/cefafb6d-3040-48a7-8dfb-b5847497ea4a/CfPD27LrBcgmtSqm3vyRX3tdFgc4yDjBIK2BnjpJ5no!/m/YQMURB1sCwAAYhCD1Rq6WwAA&a=49&b=45&bo=WAIgAwAAAAABA10!",
                "raw": "",
                "raw_upload": 0,
                "rawshoottime": 0,
                "shoottime": 0,
                "shorturl": "",
                "sloc": "M3HbeZdWUk5xjKrUQD4dab8DFEQdbAsAAA!!",
                "tag": "",
                "uploadtime": "2010-08-02 14:29:57",
                "url": "http://b45.photo.store.qq.com/psu?/cefafb6d-3040-48a7-8dfb-b5847497ea4a/CfPD27LrBcgmtSqm3vyRX3tdFgc4yDjBIK2BnjpJ5no!/b/YQMURB1sCwAAYhCD1Rq6WwAA&a=49&b=45&bo=WAIgAwAAAAABA10!",
                "width": 600,
                "yurl": 0
            },
            {
                "batchId": "0",
                "browser": 0,
                "cameratype": "",
                "cp_flag": false,
                "cp_x": 0,
                "cp_y": 0,
                "desc": "",
                "exif": {
                    "exposureCompensation": "",
                    "exposureMode": "",
                    "exposureProgram": "",
                    "exposureTime": "",
                    "flash": "",
                    "fnumber": "",
                    "focalLength": "",
                    "iso": "",
                    "lensModel": "",
                    "make": "",
                    "meteringMode": "",
                    "model": "",
                    "originalTime": ""
                },
                "forum": 0,
                "frameno": 0,
                "height": 800,
                "id": 0,
                "is_video": false,
                "is_weixin_mode": 0,
                "ismultiup": 0,
                "lloc": "MzLE6mECPkHKmBFTyX9*CScZ7xMfBAkAAA!!",
                "modifytime": 1280730578,
                "name": "IMG_0032",
                "origin": 0,
                "origin_upload": 0,
                "origin_url": "",
                "owner": "251815992",
                "ownername": "251815992",
                "photocubage": 93849,
                "phototype": 1,
                "picmark_flag": 0,
                "picrefer": 1,
                "platformId": 0,
                "platformSubId": 0,
                "poiName": "",
                "pre": "http://b52.photo.store.qq.com/psu?/cefafb6d-3040-48a7-8dfb-b5847497ea4a/N9tqsv4n8LJt0L9ppa7V9dMDYkWRL*viV9tVnOz2xsQ!/m/YZtuFBxNWgAAYhnvEx8ECQAA&a=47&b=52&bo=WAIgAwAAAAABA10!",
                "raw": "",
                "raw_upload": 0,
                "rawshoottime": 0,
                "shoottime": 0,
                "shorturl": "",
                "sloc": "M9nS1B*HEENXorqiMntNAEubbhQcTVoAAA!!",
                "tag": "",
                "uploadtime": "2010-08-02 14:29:38",
                "url": "http://b52.photo.store.qq.com/psu?/cefafb6d-3040-48a7-8dfb-b5847497ea4a/N9tqsv4n8LJt0L9ppa7V9dMDYkWRL*viV9tVnOz2xsQ!/b/YZtuFBxNWgAAYhnvEx8ECQAA&a=47&b=52&bo=WAIgAwAAAAABA10!",
                "width": 600,
                "yurl": 0
            },
            {
                "batchId": "0",
                "browser": 0,
                "cameratype": "",
                "cp_flag": false,
                "cp_x": 0,
                "cp_y": 0,
                "desc": "",
                "exif": {
                    "exposureCompensation": "",
                    "exposureMode": "",
                    "exposureProgram": "",
                    "exposureTime": "",
                    "flash": "",
                    "fnumber": "",
                    "focalLength": "",
                    "iso": "",
                    "lensModel": "",
                    "make": "",
                    "meteringMode": "",
                    "model": "",
                    "originalTime": ""
                },
                "forum": 0,
                "frameno": 0,
                "height": 503,
                "id": 0,
                "is_video": false,
                "is_weixin_mode": 0,
                "ismultiup": 0,
                "lloc": "M0tsjay.o0nmsDWVy9reAYlTktgat1oAAA!!",
                "modifytime": 1280549757,
                "name": "DSC01835",
                "origin": 0,
                "origin_upload": 0,
                "origin_url": "",
                "owner": "251815992",
                "ownername": "251815992",
                "photocubage": 233917,
                "phototype": 1,
                "picmark_flag": 0,
                "picrefer": 1,
                "platformId": 0,
                "platformSubId": 0,
                "poiName": "",
                "pre": "http://b45.photo.store.qq.com/psu?/cefafb6d-3040-48a7-8dfb-b5847497ea4a/Mneh5xn3QObJNstbTGVzj*a1rioQlHN8zcj8wjvbrVc!/m/YXvpfht3TwAAYlOS2Bq3WgAA&a=46&b=45&bo=ngL3AQAAAAABA04!",
                "raw": "",
                "raw_upload": 0,
                "rawshoottime": 0,
                "shoottime": 0,
                "shorturl": "",
                "sloc": "M9cxBuYfFkKdnX07ptNgrcd76X4bd08AAA!!",
                "tag": "",
                "uploadtime": "2010-07-31 12:15:57",
                "url": "http://b45.photo.store.qq.com/psu?/cefafb6d-3040-48a7-8dfb-b5847497ea4a/Mneh5xn3QObJNstbTGVzj*a1rioQlHN8zcj8wjvbrVc!/b/YXvpfht3TwAAYlOS2Bq3WgAA&a=46&b=45&bo=ngL3AQAAAAABA04!",
                "width": 670,
                "yurl": 0
            },
            {
                "batchId": "0",
                "browser": 0,
                "cameratype": "",
                "cp_flag": false,
                "cp_x": 0,
                "cp_y": 0,
                "desc": "",
                "exif": {
                    "exposureCompensation": "",
                    "exposureMode": "",
                    "exposureProgram": "",
                    "exposureTime": "",
                    "flash": "",
                    "fnumber": "",
                    "focalLength": "",
                    "iso": "",
                    "lensModel": "",
                    "make": "",
                    "meteringMode": "",
                    "model": "",
                    "originalTime": ""
                },
                "forum": 0,
                "frameno": 0,
                "height": 428,
                "id": 0,
                "is_video": false,
                "is_weixin_mode": 0,
                "ismultiup": 0,
                "lloc": "M1*MGdqXwUpxnTZn1wBDeP94v8IH4C8AAA!!",
                "modifytime": 1230898896,
                "name": "orbox3 ",
                "origin": 0,
                "origin_upload": 0,
                "origin_url": "",
                "owner": "251815992",
                "ownername": "251815992",
                "photocubage": 41832,
                "phototype": 1,
                "picmark_flag": 0,
                "picrefer": 0,
                "platformId": 0,
                "platformSubId": 0,
                "poiName": "",
                "pre": "http://b13.photo.store.qq.com/psu?/cefafb6d-3040-48a7-8dfb-b5847497ea4a/Cs8fnWSqDPBsv*M4V.IwEDXlyqV.OOXO45OC1AzsoaE!/m/YcS5wgfbLwAAYni*wgfgLwAA&bo=twGsAQAAAAABADw!",
                "raw": "",
                "raw_upload": 0,
                "rawshoottime": 0,
                "shoottime": 0,
                "shorturl": "",
                "sloc": "M27NZzvXIE64lWAyV48BCKrEucIH2y8AAA!!",
                "tag": "",
                "uploadtime": "2009-01-02 20:21:36",
                "url": "http://b13.photo.store.qq.com/psu?/cefafb6d-3040-48a7-8dfb-b5847497ea4a/Cs8fnWSqDPBsv*M4V.IwEDXlyqV.OOXO45OC1AzsoaE!/b/YcS5wgfbLwAAYni*wgfgLwAA&bo=twGsAQAAAAABADw!",
                "width": 439,
                "yurl": 0
            },
            {
                "batchId": "0",
                "browser": 0,
                "cameratype": "",
                "cp_flag": false,
                "cp_x": 0,
                "cp_y": 0,
                "desc": "",
                "exif": {
                    "exposureCompensation": "",
                    "exposureMode": "",
                    "exposureProgram": "",
                    "exposureTime": "",
                    "flash": "",
                    "fnumber": "",
                    "focalLength": "",
                    "iso": "",
                    "lensModel": "",
                    "make": "",
                    "meteringMode": "",
                    "model": "",
                    "originalTime": ""
                },
                "forum": 0,
                "frameno": 0,
                "height": 541,
                "id": 0,
                "is_video": false,
                "is_weixin_mode": 0,
                "ismultiup": 0,
                "lloc": "M*mk13OgmUyBvFoHtZEF7Z3sddAHei8AAA!!",
                "modifytime": 1230898892,
                "name": "orbox2 ",
                "origin": 0,
                "origin_upload": 0,
                "origin_url": "",
                "owner": "251815992",
                "ownername": "251815992",
                "photocubage": 26114,
                "phototype": 1,
                "picmark_flag": 0,
                "picrefer": 0,
                "platformId": 0,
                "platformSubId": 0,
                "poiName": "",
                "pre": "http://b13.photo.store.qq.com/psu?/cefafb6d-3040-48a7-8dfb-b5847497ea4a/pOJ42I62ECcAda244oVFo31GitPPHWlfWNvTa0VxKwg!/m/YQJeygfNLgAAYux10Ad6LwAA&bo=IAIdAgAAAAABABo!",
                "raw": "",
                "raw_upload": 0,
                "rawshoottime": 0,
                "shoottime": 0,
                "shorturl": "",
                "sloc": "M3MR0IyCMEZeq1x9WN3.JhoCXsoHzS4AAA!!",
                "tag": "",
                "uploadtime": "2009-01-02 20:21:32",
                "url": "http://b13.photo.store.qq.com/psu?/cefafb6d-3040-48a7-8dfb-b5847497ea4a/pOJ42I62ECcAda244oVFo31GitPPHWlfWNvTa0VxKwg!/b/YQJeygfNLgAAYux10Ad6LwAA&bo=IAIdAgAAAAABABo!",
                "width": 544,
                "yurl": 0
            },
            {
                "batchId": "0",
                "browser": 0,
                "cameratype": "",
                "cp_flag": false,
                "cp_x": 0,
                "cp_y": 0,
                "desc": "",
                "exif": {
                    "exposureCompensation": "",
                    "exposureMode": "",
                    "exposureProgram": "",
                    "exposureTime": "",
                    "flash": "",
                    "fnumber": "",
                    "focalLength": "",
                    "iso": "",
                    "lensModel": "",
                    "make": "",
                    "meteringMode": "",
                    "model": "",
                    "originalTime": ""
                },
                "forum": 0,
                "frameno": 0,
                "height": 502,
                "id": 0,
                "is_video": false,
                "is_weixin_mode": 0,
                "ismultiup": 0,
                "lloc": "M4YE*TsJCEOlqsr*ir1HyWq.tHQC0.cAAA!!",
                "modifytime": 1230898887,
                "name": "orbox1 ",
                "origin": 0,
                "origin_upload": 0,
                "origin_url": "",
                "owner": "251815992",
                "ownername": "251815992",
                "photocubage": 24168,
                "phototype": 1,
                "picmark_flag": 0,
                "picrefer": 0,
                "platformId": 0,
                "platformSubId": 0,
                "poiName": "",
                "pre": "http://b4.photo.store.qq.com/psu?/cefafb6d-3040-48a7-8dfb-b5847497ea4a/RggBuXbEuH8WqXTVTuSJhtUgbwSW08Nwww5KYcaD.TY!/m/YdXWyAdgLwAAYr60dALT5wAA&a=13&b=4&bo=YwL2AQAAAAABALE!",
                "raw": "",
                "raw_upload": 0,
                "rawshoottime": 0,
                "shoottime": 0,
                "shorturl": "",
                "sloc": "Mzksy6vTlUggg44bPvfbpG*V1sgHYC8AAA!!",
                "tag": "",
                "uploadtime": "2009-01-02 20:21:27",
                "url": "http://b4.photo.store.qq.com/psu?/cefafb6d-3040-48a7-8dfb-b5847497ea4a/RggBuXbEuH8WqXTVTuSJhtUgbwSW08Nwww5KYcaD.TY!/b/YdXWyAdgLwAAYr60dALT5wAA&a=13&b=4&bo=YwL2AQAAAAABALE!",
                "width": 611,
                "yurl": 0
            },
            {
                "batchId": "0",
                "browser": 0,
                "cameratype": "",
                "cp_flag": false,
                "cp_x": 0,
                "cp_y": 0,
                "desc": "",
                "exif": {
                    "exposureCompensation": "",
                    "exposureMode": "",
                    "exposureProgram": "",
                    "exposureTime": "",
                    "flash": "",
                    "fnumber": "",
                    "focalLength": "",
                    "iso": "",
                    "lensModel": "",
                    "make": "",
                    "meteringMode": "",
                    "model": "",
                    "originalTime": ""
                },
                "forum": 0,
                "frameno": 0,
                "height": 484,
                "id": 0,
                "is_video": false,
                "is_weixin_mode": 0,
                "ismultiup": 0,
                "lloc": "MxdsNUjhTUW.pHP9lrawtBOUJXMCgekAAA!!",
                "modifytime": 1230898885,
                "name": "orbox4 ",
                "origin": 0,
                "origin_upload": 0,
                "origin_url": "",
                "owner": "251815992",
                "ownername": "251815992",
                "photocubage": 37873,
                "phototype": 1,
                "picmark_flag": 0,
                "picrefer": 0,
                "platformId": 0,
                "platformSubId": 0,
                "poiName": "",
                "pre": "http://b4.photo.store.qq.com/psu?/cefafb6d-3040-48a7-8dfb-b5847497ea4a/QAJSitl.epvbBpauq5KTCvNQfSh6P9N4sNXry2S1V5c!/m/YX7VpAADqwAAYpQlcwKB6QAA&a=1&b=4&bo=0AHkAQAAAAABABM!",
                "raw": "",
                "raw_upload": 0,
                "rawshoottime": 0,
                "shoottime": 0,
                "shorturl": "",
                "sloc": "M*EJHkCdukBchYP3c5vC5R9.1aQAA6sAAA!!",
                "tag": "",
                "uploadtime": "2009-01-02 20:21:25",
                "url": "http://b4.photo.store.qq.com/psu?/cefafb6d-3040-48a7-8dfb-b5847497ea4a/QAJSitl.epvbBpauq5KTCvNQfSh6P9N4sNXry2S1V5c!/b/YX7VpAADqwAAYpQlcwKB6QAA&a=1&b=4&bo=0AHkAQAAAAABABM!",
                "width": 464,
                "yurl": 0
            },
            {
                "batchId": "0",
                "browser": 0,
                "cameratype": "",
                "cp_flag": false,
                "cp_x": 0,
                "cp_y": 0,
                "desc": "",
                "exif": {
                    "exposureCompensation": "",
                    "exposureMode": "",
                    "exposureProgram": "",
                    "exposureTime": "",
                    "flash": "",
                    "fnumber": "",
                    "focalLength": "",
                    "iso": "",
                    "lensModel": "",
                    "make": "",
                    "meteringMode": "",
                    "model": "",
                    "originalTime": ""
                },
                "forum": 0,
                "frameno": 0,
                "height": 800,
                "id": 0,
                "is_video": false,
                "is_weixin_mode": 0,
                "ismultiup": 0,
                "lloc": "M2spm2x4i0sAo2U*pHLLBrAn96sDK2YAAA!!",
                "modifytime": 1211636829,
                "name": "9318278 ",
                "origin": 0,
                "origin_upload": 0,
                "origin_url": "",
                "owner": "251815992",
                "ownername": "251815992",
                "photocubage": 88958,
                "phototype": 1,
                "picmark_flag": 0,
                "picrefer": 0,
                "platformId": 0,
                "platformSubId": 0,
                "poiName": "",
                "pre": "http://b6.photo.store.qq.com/psu?/cefafb6d-3040-48a7-8dfb-b5847497ea4a/OjMqVOLfJg5BTbahKmfdXrAs7y9q7RG5qzxabOcfBzo!/m/YfPzPAQ.JgAAYif3qwMrZgAA&a=7&b=6&bo=MwIgAwAAAAABADU!",
                "raw": "",
                "raw_upload": 0,
                "rawshoottime": 0,
                "shoottime": 0,
                "shorturl": "",
                "sloc": "M9fVCWeN7UC7u45BIKU3*ULz8zwEPiYAAA!!",
                "tag": "",
                "uploadtime": "2008-05-24 21:47:09",
                "url": "http://b6.photo.store.qq.com/psu?/cefafb6d-3040-48a7-8dfb-b5847497ea4a/OjMqVOLfJg5BTbahKmfdXrAs7y9q7RG5qzxabOcfBzo!/b/YfPzPAQ.JgAAYif3qwMrZgAA&a=7&b=6&bo=MwIgAwAAAAABADU!",
                "width": 563,
                "yurl": 0
            },
            {
                "batchId": "0",
                "browser": 0,
                "cameratype": "",
                "cp_flag": false,
                "cp_x": 0,
                "cp_y": 0,
                "desc": "",
                "exif": {
                    "exposureCompensation": "",
                    "exposureMode": "",
                    "exposureProgram": "",
                    "exposureTime": "",
                    "flash": "",
                    "fnumber": "",
                    "focalLength": "",
                    "iso": "",
                    "lensModel": "",
                    "make": "",
                    "meteringMode": "",
                    "model": "",
                    "originalTime": ""
                },
                "forum": 0,
                "frameno": 0,
                "height": 800,
                "id": 0,
                "is_video": false,
                "is_weixin_mode": 0,
                "ismultiup": 0,
                "lloc": "Mxg2Vs1uqkhBsFpaFqmMRyghEQED5hcAAA!!",
                "modifytime": 1211636824,
                "name": "9211884 ",
                "origin": 0,
                "origin_upload": 0,
                "origin_url": "",
                "owner": "251815992",
                "ownername": "251815992",
                "photocubage": 94488,
                "phototype": 1,
                "picmark_flag": 0,
                "picrefer": 0,
                "platformId": 0,
                "platformSubId": 0,
                "poiName": "",
                "pre": "http://b5.photo.store.qq.com/psu?/cefafb6d-3040-48a7-8dfb-b5847497ea4a/57ldPde9gjnrABGNrXS8jcp0izbr6ytDCrQlNsVAQ14!/m/YQvNDgPJEgAAYiERAQPmFwAA&bo=OAIgAwAAAAABAD4!",
                "raw": "",
                "raw_upload": 0,
                "rawshoottime": 0,
                "shoottime": 0,
                "shorturl": "",
                "sloc": "M9TNxquVREQlrVXtF3kIMVoLzQ4DyRIAAA!!",
                "tag": "",
                "uploadtime": "2008-05-24 21:47:04",
                "url": "http://b5.photo.store.qq.com/psu?/cefafb6d-3040-48a7-8dfb-b5847497ea4a/57ldPde9gjnrABGNrXS8jcp0izbr6ytDCrQlNsVAQ14!/b/YQvNDgPJEgAAYiERAQPmFwAA&bo=OAIgAwAAAAABAD4!",
                "width": 568,
                "yurl": 0
            },
            {
                "batchId": "0",
                "browser": 0,
                "cameratype": "",
                "cp_flag": false,
                "cp_x": 0,
                "cp_y": 0,
                "desc": "",
                "exif": {
                    "exposureCompensation": "",
                    "exposureMode": "",
                    "exposureProgram": "",
                    "exposureTime": "",
                    "flash": "",
                    "fnumber": "",
                    "focalLength": "",
                    "iso": "",
                    "lensModel": "",
                    "make": "",
                    "meteringMode": "",
                    "model": "",
                    "originalTime": ""
                },
                "forum": 0,
                "frameno": 0,
                "height": 800,
                "id": 0,
                "is_video": false,
                "is_weixin_mode": 0,
                "ismultiup": 0,
                "lloc": "M5WnQNDVXEofiR2.TO8P*v2..z8EAAcAAA!!",
                "modifytime": 1211636820,
                "name": "8976756 ",
                "origin": 0,
                "origin_upload": 0,
                "origin_url": "",
                "owner": "251815992",
                "ownername": "251815992",
                "photocubage": 104338,
                "phototype": 1,
                "picmark_flag": 0,
                "picrefer": 0,
                "platformId": 0,
                "platformSubId": 0,
                "poiName": "",
                "pre": "http://b7.photo.store.qq.com/psu?/cefafb6d-3040-48a7-8dfb-b5847497ea4a/jyd*4*rWKNHMTCUsnYXlZgCW2mEZOTav94*.iKTVKyg!/m/YQDeOQQfJgAAYr77PwQABwAA&bo=IwIgAwAAAAABACU!",
                "raw": "",
                "raw_upload": 0,
                "rawshoottime": 0,
                "shoottime": 0,
                "shorturl": "",
                "sloc": "M5t8ALkNFUC1nAK76cl8EeMA3jkEHyYAAA!!",
                "tag": "",
                "uploadtime": "2008-05-24 21:47:00",
                "url": "http://b7.photo.store.qq.com/psu?/cefafb6d-3040-48a7-8dfb-b5847497ea4a/jyd*4*rWKNHMTCUsnYXlZgCW2mEZOTav94*.iKTVKyg!/b/YQDeOQQfJgAAYr77PwQABwAA&bo=IwIgAwAAAAABACU!",
                "width": 547,
                "yurl": 0
            },
            {
                "batchId": "0",
                "browser": 0,
                "cameratype": "",
                "cp_flag": false,
                "cp_x": 0,
                "cp_y": 0,
                "desc": "",
                "exif": {
                    "exposureCompensation": "",
                    "exposureMode": "",
                    "exposureProgram": "",
                    "exposureTime": "",
                    "flash": "",
                    "fnumber": "",
                    "focalLength": "",
                    "iso": "",
                    "lensModel": "",
                    "make": "",
                    "meteringMode": "",
                    "model": "",
                    "originalTime": ""
                },
                "forum": 1,
                "frameno": 0,
                "height": 327,
                "id": 0,
                "is_video": false,
                "is_weixin_mode": 0,
                "ismultiup": 0,
                "lloc": "M70oNXnevEz2qsQkyeIZK5mxCP4CAwkAAA!!",
                "modifytime": 1201536053,
                "name": "寝室图片 ",
                "origin": 0,
                "origin_upload": 0,
                "origin_url": "",
                "owner": "251815992",
                "ownername": "251815992",
                "photocubage": 37452,
                "phototype": 1,
                "picmark_flag": 0,
                "picrefer": 0,
                "platformId": 0,
                "platformSubId": 0,
                "poiName": "",
                "pre": "http://b5.photo.store.qq.com/psu?/cefafb6d-3040-48a7-8dfb-b5847497ea4a/UONBD51fP5N*phsmdYAeDmGnAQKi4Rl1j8oa1RWXVeU!/m/YekacAJ.pQAAYrEI*gIDCQAA&a=4&b=5&bo=fQFHAQAAAAABAB0!",
                "raw": "",
                "raw_upload": 0,
                "rawshoottime": 0,
                "shoottime": 0,
                "shorturl": "",
                "sloc": "M4TiBISaA0hjjKjMWslU8pDpGnACfqUAAA!!",
                "tag": "",
                "uploadtime": "2008-01-29 00:00:53",
                "url": "http://b5.photo.store.qq.com/psu?/cefafb6d-3040-48a7-8dfb-b5847497ea4a/UONBD51fP5N*phsmdYAeDmGnAQKi4Rl1j8oa1RWXVeU!/b/YekacAJ.pQAAYrEI*gIDCQAA&a=4&b=5&bo=fQFHAQAAAAABAB0!",
                "width": 381,
                "yurl": 0
            },
            {
                "batchId": "0",
                "browser": 0,
                "cameratype": "",
                "cp_flag": false,
                "cp_x": 0,
                "cp_y": 0,
                "desc": "",
                "exif": {
                    "exposureCompensation": "",
                    "exposureMode": "",
                    "exposureProgram": "",
                    "exposureTime": "",
                    "flash": "",
                    "fnumber": "",
                    "focalLength": "",
                    "iso": "",
                    "lensModel": "",
                    "make": "",
                    "meteringMode": "",
                    "model": "",
                    "originalTime": ""
                },
                "forum": 0,
                "frameno": 0,
                "height": 65,
                "id": 0,
                "is_video": false,
                "is_weixin_mode": 0,
                "ismultiup": 0,
                "lloc": "MzezVRUwVUHPoZ1talZY4eFtHAQD6wgAAA!!",
                "modifytime": 1201536052,
                "name": "开发图片 ",
                "origin": 0,
                "origin_upload": 0,
                "origin_url": "",
                "owner": "251815992",
                "ownername": "251815992",
                "photocubage": 4990,
                "phototype": 1,
                "picmark_flag": 0,
                "picrefer": 0,
                "platformId": 0,
                "platformSubId": 0,
                "poiName": "",
                "pre": "http://b5.photo.store.qq.com/psu?/cefafb6d-3040-48a7-8dfb-b5847497ea4a/rwHTZwU9s9vp6aReTpNrMtCxhbsayaTjRUeNnnhgcbU!/m/YdUB*gIBCQAAYm0cBAPrCAAA&bo=EQFBAAAAAAABAHY!",
                "raw": "",
                "raw_upload": 0,
                "rawshoottime": 0,
                "shoottime": 0,
                "shorturl": "",
                "sloc": "MzRc6D9Kv0UXgM3Z2wK7VMHVAf4CAQkAAA!!",
                "tag": "",
                "uploadtime": "2008-01-29 00:00:52",
                "url": "http://b5.photo.store.qq.com/psu?/cefafb6d-3040-48a7-8dfb-b5847497ea4a/rwHTZwU9s9vp6aReTpNrMtCxhbsayaTjRUeNnnhgcbU!/b/YdUB*gIBCQAAYm0cBAPrCAAA&bo=EQFBAAAAAAABAHY!",
                "width": 273,
                "yurl": 0
            },
            {
                "batchId": "0",
                "browser": 0,
                "cameratype": "",
                "cp_flag": false,
                "cp_x": 0,
                "cp_y": 0,
                "desc": "",
                "exif": {
                    "exposureCompensation": "",
                    "exposureMode": "",
                    "exposureProgram": "",
                    "exposureTime": "",
                    "flash": "",
                    "fnumber": "",
                    "focalLength": "",
                    "iso": "",
                    "lensModel": "",
                    "make": "",
                    "meteringMode": "",
                    "model": "",
                    "originalTime": ""
                },
                "forum": 0,
                "frameno": 0,
                "height": 421,
                "id": 0,
                "is_video": false,
                "is_weixin_mode": 0,
                "ismultiup": 0,
                "lloc": "M5r7xkNU6E6mjBXIINGrGAMqKHMCOpMAAA!!",
                "modifytime": 1200756336,
                "name": "相册伴侣.jpg",
                "origin": 0,
                "origin_upload": 0,
                "origin_url": "",
                "owner": "251815992",
                "ownername": "251815992",
                "photocubage": 68693,
                "phototype": 1,
                "picmark_flag": 0,
                "picrefer": 0,
                "platformId": 0,
                "platformSubId": 0,
                "poiName": "",
                "pre": "http://b4.photo.store.qq.com/psu?/cefafb6d-3040-48a7-8dfb-b5847497ea4a/TzkHLBEWeUkbzPNMg30Cyv.6MCEtyAXWIzm1MpUU*4o!/m/YU*jYwKQlAAAYioocwI6kwAA&bo=4gGlAQAAAAABAGA!",
                "raw": "",
                "raw_upload": 0,
                "rawshoottime": 0,
                "shoottime": 0,
                "shorturl": "",
                "sloc": "M1hp40NG00g2iNb3J5oiuBtP42MCkJQAAA!!",
                "tag": "",
                "uploadtime": "2008-01-19 23:25:36",
                "url": "http://b4.photo.store.qq.com/psu?/cefafb6d-3040-48a7-8dfb-b5847497ea4a/TzkHLBEWeUkbzPNMg30Cyv.6MCEtyAXWIzm1MpUU*4o!/b/YU*jYwKQlAAAYioocwI6kwAA&bo=4gGlAQAAAAABAGA!",
                "width": 482,
                "yurl": 0
            },
            {
                "batchId": "0",
                "browser": 0,
                "cameratype": "",
                "cp_flag": false,
                "cp_x": 0,
                "cp_y": 0,
                "desc": "",
                "exif": {
                    "exposureCompensation": "",
                    "exposureMode": "",
                    "exposureProgram": "",
                    "exposureTime": "",
                    "flash": "",
                    "fnumber": "",
                    "focalLength": "",
                    "iso": "",
                    "lensModel": "",
                    "make": "",
                    "meteringMode": "",
                    "model": "",
                    "originalTime": ""
                },
                "forum": 0,
                "frameno": 0,
                "height": 115,
                "id": 0,
                "is_video": false,
                "is_weixin_mode": 0,
                "ismultiup": 0,
                "lloc": "M9MiKcL4EUmcher9LhKBgxwImm4CDpIAAA!!",
                "modifytime": 1200754345,
                "name": "风云赛伴侣.JPG",
                "origin": 0,
                "origin_upload": 0,
                "origin_url": "",
                "owner": "251815992",
                "ownername": "251815992",
                "photocubage": 20651,
                "phototype": 1,
                "picmark_flag": 0,
                "picrefer": 0,
                "platformId": 0,
                "platformSubId": 0,
                "poiName": "",
                "pre": "http://b4.photo.store.qq.com/psu?/cefafb6d-3040-48a7-8dfb-b5847497ea4a/J7SoyjakYnoWyXC4ffeBdOeaFc6qBo1LTZGvGKAJSOM!/m/YcEbcAJ9kwAAYgiabgIOkgAA&bo=mAJzAAAAAAABAM4!",
                "raw": "",
                "raw_upload": 0,
                "rawshoottime": 0,
                "shoottime": 0,
                "shorturl": "",
                "sloc": "M3SY.2QXm0xQtc5Bj1YRR9HBG3ACfZMAAA!!",
                "tag": "",
                "uploadtime": "2008-01-19 22:52:25",
                "url": "http://b4.photo.store.qq.com/psu?/cefafb6d-3040-48a7-8dfb-b5847497ea4a/J7SoyjakYnoWyXC4ffeBdOeaFc6qBo1LTZGvGKAJSOM!/b/YcEbcAJ9kwAAYgiabgIOkgAA&bo=mAJzAAAAAAABAM4!",
                "width": 664,
                "yurl": 0
            }
        ],
        "t": "",
        "topic": {
            "bitmap": "11000010",
            "browser": 0,
            "classid": 101,
            "comment": 1,
            "cover_id": "M3MR0IyCMEZeq1x9WN3.JhoCXsoHzS4AAA!!",
            "createtime": 1199447918,
            "desc": "邮箱：rainbow_pencil@yahoo.com.cn\r\n密码：123456",
            "handset": 0,
            "id": "cefafb6d-3040-48a7-8dfb-b5847497ea4a",
            "is_share_album": 0,
            "lastuploadtime": 1280925179,
            "modifytime": 1420720177,
            "name": "...",
            "ownerName": "251815992",
            "ownerUin": "251815992",
            "pre": "http://b13.photo.store.qq.com/psu?/cefafb6d-3040-48a7-8dfb-b5847497ea4a/pOJ42I62ECcAda244oVFo31GitPPHWlfWNvTa0VxKwg!/a/YQJeygfNLgAAYux10Ad6LwAA",
            "priv": 3,
            "pypriv": 3,
            "share_album_owner": 0,
            "total": 15,
            "url": "http://b13.photo.store.qq.com/psu?/cefafb6d-3040-48a7-8dfb-b5847497ea4a/pOJ42I62ECcAda244oVFo31GitPPHWlfWNvTa0VxKwg!/b/YQJeygfNLgAAYux10Ad6LwAA",
            "viewtype": 0
        },
        "totalInAlbum": 15,
        "totalInPage": 15
    }
}